kedro_prefect_oliver/__init__.py
kedro_prefect_oliver/infrastructure.py
kedro_prefect_oliver/register.py
kedro_prefect_oliver-0.1.18.dist-info/LICENSE
kedro_prefect_oliver-0.1.18.dist-info/METADATA
kedro_prefect_oliver-0.1.18.dist-info/WHEEL
kedro_prefect_oliver-0.1.18.dist-info/top_level.txt
kedro_prefect_oliver-0.1.18.dist-info/RECORD
