Metadata-Version: 2.1
Name: kedro-prefect-oliver
Version: 0.1.18
Summary: Kedro-Prefect integration library
Author-email: Oliver OTL <dev@olivetreeholdings.com>
Classifier: Development Status :: 4 - Beta
Classifier: Intended Audience :: Developers
Classifier: License :: OSI Approved :: MIT License
Classifier: Programming Language :: Python :: 3.8
Classifier: Programming Language :: Python :: 3.9
Classifier: Programming Language :: Python :: 3.10
Requires-Python: >=3.8
License-File: LICENSE
Requires-Dist: kedro <0.19.0,>=0.18.0
Requires-Dist: prefect >=2.8.2
Provides-Extra: spark
Provides-Extra: test
Requires-Dist: bandit[toml] ==1.7.4 ; extra == 'test'
Requires-Dist: black ==22.1.0 ; extra == 'test'
Requires-Dist: check-manifest ==0.48 ; extra == 'test'
Requires-Dist: flake8-bugbear ==22.1.11 ; extra == 'test'
Requires-Dist: flake8-docstrings ; extra == 'test'
Requires-Dist: flake8-formatter-junit-xml ; extra == 'test'
Requires-Dist: flake8 ==4.0.1 ; extra == 'test'
Requires-Dist: pre-commit ==2.17.0 ; extra == 'test'
Requires-Dist: pylint ==2.12.2 ; extra == 'test'
Requires-Dist: pylint-junit ; extra == 'test'
Requires-Dist: pytest-cov ==3.0.0 ; extra == 'test'
Requires-Dist: pytest-mock <3.7.1 ; extra == 'test'
Requires-Dist: pytest-runner ; extra == 'test'
Requires-Dist: pytest ==7.1.0 ; extra == 'test'
Requires-Dist: pytest-github-actions-annotate-failures ; extra == 'test'
Requires-Dist: shellcheck-py ==0.8.0.4 ; extra == 'test'
